httpz/__init__.py
httpz/http_status_code.py
httpz/http_status_code_category_enum.py
httpz/http_status_code_enum.py
httpz/http_status_codes.py
httpz/status_codes.py
tests/__init__.py
tests/test_http_status_codes.py
httpz-1.0.dist-info/LICENSE.txt
httpz-1.0.dist-info/METADATA
httpz-1.0.dist-info/WHEEL
httpz-1.0.dist-info/top_level.txt
httpz-1.0.dist-info/RECORD
