Metadata-Version: 2.1
Name: httpz
Version: 1.0
Summary: HTTP Status code utils
Home-page: https://github.com/Julian-Nash/httpz
Author: Julian Nash
Author-email: julianjamesnash@gmail.com
License: UNKNOWN
Project-URL: Bug Tracker, https://github.com/Julian-Nash/httpz
Project-URL: Documentation, https://github.com/Julian-Nash/httpz
Project-URL: Source Code, https://github.com/Julian-Nash/httpz
Keywords: http status codes
Platform: UNKNOWN
Classifier: Intended Audience :: Developers
Classifier: License :: OSI Approved :: MIT License
Classifier: Programming Language :: Python :: 3.6
Classifier: Programming Language :: Python :: 3.7
Classifier: Programming Language :: Python :: 3.8
